aqueduct_llm/__init__.py
aqueduct_llm/dolly_v2_3b.py
aqueduct_llm/dolly_v2_7b.py
aqueduct_llm/llama_7b.py
aqueduct_llm/vicuna_7b.py
aqueduct_llm/utils/__init__.py
aqueduct_llm/utils/dolly_instruct_pipeline.py
aqueduct_llm-0.0.1.dist-info/METADATA
aqueduct_llm-0.0.1.dist-info/WHEEL
aqueduct_llm-0.0.1.dist-info/top_level.txt
aqueduct_llm-0.0.1.dist-info/RECORD
